atrhub/__init__.py
atrhub/cli.py
atrhub/files.py
atrhub-0.4.6.dist-info/METADATA
atrhub-0.4.6.dist-info/WHEEL
atrhub-0.4.6.dist-info/entry_points.txt
atrhub-0.4.6.dist-info/top_level.txt
atrhub-0.4.6.dist-info/RECORD
