Metadata-Version: 2.1
Name: atrhub
Version: 0.4.6
Summary: ATR xml files handler
Home-page: https://www.gisce.net
Author: Xavi Torelló
Author-email: devel@gisce.net
License: General Public Licence 3
Platform: UNKNOWN
Classifier: Programming Language :: Python
Classifier: Programming Language :: Python :: 2.7
Classifier: Programming Language :: Python :: 3
Classifier: Programming Language :: Python :: 3.6
Classifier: Programming Language :: Python :: 3.7
Provides: atrhub
Requires-Dist: gestionatr
Requires-Dist: click
Requires-Dist: future ; python_version < "3"
Requires-Dist: pathlib ; python_version < "3.5"
Requires-Dist: configparser ; python_version < "3.5"
